LICENSE
README.md
pyproject.toml
setup.py
Finding_minimum_subnet/__init__.py
Finding_minimum_subnet/common_utils.py
Finding_minimum_subnet/example.py
Finding_minimum_subnet/ipv4_utils.py
Finding_minimum_subnet/ipv6_utils.py
Finding_minimum_subnet/main.py
Finding_minimum_subnet/test_ipv4_utils.py
Finding_minimum_subnet/test_ipv6_utils.py
Finding_minimum_subnet.egg-info/PKG-INFO
Finding_minimum_subnet.egg-info/SOURCES.txt
Finding_minimum_subnet.egg-info/dependency_links.txt
Finding_minimum_subnet.egg-info/requires.txt
Finding_minimum_subnet.egg-info/top_level.txt